{"updated": "2025-03-14 15:22", "items": [{"symbol": "HOOD", "timeframe": 60, "strategy": "Revival2", "realized": 9765.66, "change": 784.51, "unrealized": -1446.83, "unrealizedValueChange": -14.47, "realizedValueChange": 97.66, "marketValue": 18318.83, "marketValueChange": 83.19, "tradeNum": 87, "gainNum": 43, "loseNum": 5, "fromDate": "2024-03-12 19:30:00", "toDate": "2025-03-14 14:30:00", "positionSize": 148, "positionPrice": 48.98, "startingCash": 10000, "cash": 12517.23, "arguments": "(BUY:SMA30 SELL:BollTop Cash 10K)", "winner_rate": 0.9, "extend": ""}, {"symbol": "NVDA", "timeframe": 60, "strategy": "Vivid2", "realized": 4592.59, "change": 468.09, "unrealized": 443.46, "unrealizedValueChange": 4.43, "realizedValueChange": 45.93, "marketValue": 15036.05, "marketValueChange": 50.36, "tradeNum": 107, "gainNum": 52, "loseNum": 4, "fromDate": "2024-03-12 19:30:00", "toDate": "2025-03-14 14:30:00", "positionSize": 104, "positionPrice": 116.72, "startingCash": 10000, "cash": 2454.13, "arguments": "(BollBot x BollTop Cash 10K)", "winner_rate": 0.93, "extend": ""}, {"symbol": "BX", "timeframe": 60, "strategy": "Revival2", "realized": 4071.89, "change": 352.51, "unrealized": -1503.96, "unrealizedValueChange": -15.04, "realizedValueChange": 40.72, "marketValue": 12567.93, "marketValueChange": 25.68, "tradeNum": 98, "gainNum": 45, "loseNum": 5, "fromDate": "2024-03-12 19:30:00", "toDate": "2025-03-14 14:30:00", "positionSize": 70, "positionPrice": 162.04, "startingCash": 10000, "cash": 2729.43, "arguments": "(BUY:SMA30 SELL:BollTop Cash 10K)", "winner_rate": 0.9, "extend": ""}, {"symbol": "BX", "timeframe": 60, "strategy": "Stoch2", "realized": 3306.07, "change": 326.35, "unrealized": -1654.13, "unrealizedValueChange": -16.54, "realizedValueChange": 33.06, "marketValue": 11651.95, "marketValueChange": 16.52, "tradeNum": 155, "gainNum": 74, "loseNum": 8, "fromDate": "2024-03-12 19:30:00", "toDate": "2025-03-14 14:30:00", "positionSize": 74, "positionPrice": 162.9, "startingCash": 10000, "cash": 1251.25, "arguments": "(BollBot x BollTop Cash 10K)", "winner_rate": 0.9, "extend": ""}, {"symbol": "GS", "timeframe": 60, "strategy": "Revival2", "realized": 2076.15, "change": 210.87, "unrealized": -481.52, "unrealizedValueChange": -4.82, "realizedValueChange": 20.76, "marketValue": 11594.63, "marketValueChange": 15.95, "tradeNum": 71, "gainNum": 32, "loseNum": 3, "fromDate": "2024-03-12 19:30:00", "toDate": "2025-03-14 14:30:00", "positionSize": 8, "positionPrice": 599.81, "startingCash": 10000, "cash": 7277.67, "arguments": "(BUY:SMA30 SELL:BollTop Cash 10K)", "winner_rate": 0.91, "extend": ""}, {"symbol": "AXP", "timeframe": 60, "strategy": "Stoch2", "realized": 2118.44, "change": 231.32, "unrealized": -873.44, "unrealizedValueChange": -8.73, "realizedValueChange": 21.18, "marketValue": 11245.01, "marketValueChange": 12.45, "tradeNum": 105, "gainNum": 53, "loseNum": 2, "fromDate": "2024-03-12 19:30:00", "toDate": "2025-03-14 14:30:00", "positionSize": 39, "positionPrice": 286.32, "startingCash": 10000, "cash": 952.13, "arguments": "(BollBot x BollTop Cash 10K)", "winner_rate": 0.96, "extend": ""}, {"symbol": "UPRO", "timeframe": 60, "strategy": "Vivid2", "realized": 3188.23, "change": 326.92, "unrealized": -1969.64, "unrealizedValueChange": -19.7, "realizedValueChange": 31.88, "marketValue": 11218.59, "marketValueChange": 12.19, "tradeNum": 97, "gainNum": 49, "loseNum": 2, "fromDate": "2024-03-12 19:30:00", "toDate": "2025-03-14 14:30:00", "positionSize": 141, "positionPrice": 88.76, "startingCash": 10000, "cash": 673.18, "arguments": "(BollBot x BollTop Cash 10K)", "winner_rate": 0.96, "extend": ""}, {"symbol": "SSO", "timeframe": 60, "strategy": "Revival2", "realized": 2528.59, "change": 231.04, "unrealized": -1456.49, "unrealizedValueChange": -14.56, "realizedValueChange": 25.29, "marketValue": 11072.1, "marketValueChange": 10.72, "tradeNum": 86, "gainNum": 41, "loseNum": 2, "fromDate": "2024-03-12 19:30:00", "toDate": "2025-03-14 14:30:00", "positionSize": 131, "positionPrice": 94.43, "startingCash": 10000, "cash": 158.49, "arguments": "(BUY:SMA30 SELL:BollTop Cash 10K)", "winner_rate": 0.95, "extend": ""}]}