[{"symbol": "VST", "timeframe": 60, "strategy": "Revival2", "realized": 6999.92, "change": 612.65, "unrealized": -5022.15, "unrealizedValueChange": -50.22, "realizedValueChange": 70.0, "marketValue": 11977.77, "marketValueChange": 19.78, "tradeNum": 85, "gainNum": 36, "loseNum": 7, "fromDate": "2024-03-11 13:30:00", "toDate": "2025-03-10 19:30:00", "positionSize": 105, "positionPrice": 155.99, "startingCash": 10000, "cash": 620.97, "arguments": "(BUY:SMA30 SELL:BollTop Cash 10K)", "winner_rate": 0.84, "extend": ""}, {"symbol": "ETN", "timeframe": 60, "strategy": "Revival2", "realized": 1131.89, "change": 132.73, "unrealized": -1323.87, "unrealizedValueChange": -13.24, "realizedValueChange": 11.32, "marketValue": 9808.01, "marketValueChange": -1.92, "tradeNum": 98, "gainNum": 39, "loseNum": 12, "fromDate": "2024-03-11 13:30:00", "toDate": "2025-03-10 19:30:00", "positionSize": 35, "positionPrice": 315.18, "startingCash": 10000, "cash": 100.41, "arguments": "(BUY:SMA30 SELL:BollTop Cash 10K)", "winner_rate": 0.76, "extend": ""}, {"symbol": "AXP", "timeframe": 60, "strategy": "Revival2", "realized": 1012.55, "change": 109.38, "unrealized": -1346.34, "unrealizedValueChange": -13.46, "realizedValueChange": 10.13, "marketValue": 9666.21, "marketValueChange": -3.34, "tradeNum": 74, "gainNum": 29, "loseNum": 7, "fromDate": "2024-03-11 13:30:00", "toDate": "2025-03-10 19:30:00", "positionSize": 32, "positionPrice": 303.16, "startingCash": 10000, "cash": 1311.49, "arguments": "(BUY:SMA30 SELL:BollTop Cash 10K)", "winner_rate": 0.81, "extend": ""}, {"symbol": "NET", "timeframe": 60, "strategy": "Revival2", "realized": 3065.52, "change": 350.21, "unrealized": -736.59, "unrealizedValueChange": -7.37, "realizedValueChange": 30.66, "marketValue": 12328.93, "marketValueChange": 23.29, "tradeNum": 84, "gainNum": 31, "loseNum": 13, "fromDate": "2024-03-11 13:30:00", "toDate": "2025-03-10 19:30:00", "positionSize": 59, "positionPrice": 129.68, "startingCash": 10000, "cash": 5414.13, "arguments": "(BUY:SMA30 SELL:BollTop Cash 10K)", "winner_rate": 0.7, "extend": ""}, {"symbol": "QCOM", "timeframe": 60, "strategy": "Revival2", "realized": 226.57, "change": 28.33, "unrealized": -537.97, "unrealizedValueChange": -5.38, "realizedValueChange": 2.27, "marketValue": 9688.6, "marketValueChange": -3.11, "tradeNum": 84, "gainNum": 24, "loseNum": 18, "fromDate": "2024-03-11 13:30:00", "toDate": "2025-03-10 19:30:00", "positionSize": 50, "positionPrice": 165.86, "startingCash": 10000, "cash": 1933.6, "arguments": "(BUY:SMA30 SELL:BollTop Cash 10K)", "winner_rate": 0.57, "extend": ""}, {"symbol": "APP", "timeframe": 60, "strategy": "Revival2", "realized": 11244.57, "change": 899.71, "unrealized": -6032.89, "unrealizedValueChange": -60.33, "realizedValueChange": 112.45, "marketValue": 15211.68, "marketValueChange": 52.12, "tradeNum": 100, "gainNum": 45, "loseNum": 8, "fromDate": "2024-03-11 13:30:00", "toDate": "2025-03-10 19:30:00", "positionSize": 58, "positionPrice": 345.12, "startingCash": 10000, "cash": 1227.59, "arguments": "(BUY:SMA30 SELL:BollTop Cash 10K)", "winner_rate": 0.85, "extend": ""}, {"symbol": "CRM", "timeframe": 60, "strategy": "Revival2", "realized": -8.67, "change": 15.52, "unrealized": -1311.47, "unrealizedValueChange": -13.11, "realizedValueChange": -0.09, "marketValue": 8679.87, "marketValueChange": -13.2, "tradeNum": 80, "gainNum": 18, "loseNum": 22, "fromDate": "2024-03-11 13:30:00", "toDate": "2025-03-10 19:30:00", "positionSize": 24, "positionPrice": 329.15, "startingCash": 10000, "cash": 2091.81, "arguments": "(BUY:SMA30 SELL:BollTop Cash 10K)", "winner_rate": 0.45, "extend": ""}, {"symbol": "HOOD", "timeframe": 60, "strategy": "Revival2", "realized": 9765.66, "change": 784.51, "unrealized": -1754.49, "unrealizedValueChange": -17.54, "realizedValueChange": 97.66, "marketValue": 18011.17, "marketValueChange": 80.11, "tradeNum": 87, "gainNum": 43, "loseNum": 5, "fromDate": "2024-03-11 13:30:00", "toDate": "2025-03-10 19:30:00", "positionSize": 148, "positionPrice": 48.98, "startingCash": 10000, "cash": 12517.23, "arguments": "(BUY:SMA30 SELL:BollTop Cash 10K)", "winner_rate": 0.9, "extend": ""}, {"symbol": "SMCI", "timeframe": 60, "strategy": "Revival2", "realized": -5141.45, "change": -664.07, "unrealized": -209.17, "unrealizedValueChange": -2.09, "realizedValueChange": -51.41, "marketValue": 4649.38, "marketValueChange": -53.51, "tradeNum": 86, "gainNum": 8, "loseNum": 38, "fromDate": "2024-03-11 13:30:00", "toDate": "2025-03-10 19:30:00", "positionSize": 26, "positionPrice": 45.05, "startingCash": 10000, "cash": 3687.35, "arguments": "(BUY:SMA30 SELL:BollTop Cash 10K)", "winner_rate": 0.17, "extend": ""}, {"symbol": "SQ", "timeframe": 60, "strategy": "Revival2", "realized": 1770.15, "change": 190.66, "unrealized": -200.25, "unrealizedValueChange": -2.0, "realizedValueChange": 17.7, "marketValue": 11569.9, "marketValueChange": 15.7, "tradeNum": 72, "gainNum": 25, "loseNum": 12, "fromDate": "2024-03-11 13:30:00", "toDate": "2025-02-26 20:30:00", "positionSize": 86, "positionPrice": 89.29, "startingCash": 10000, "cash": 4091.34, "arguments": "(BUY:SMA30 SELL:BollTop Cash 10K)", "winner_rate": 0.68, "extend": ""}, {"symbol": "PYPL", "timeframe": 60, "strategy": "Revival2", "realized": 1642.38, "change": 173.28, "unrealized": -1380.5, "unrealizedValueChange": -13.8, "realizedValueChange": 16.42, "marketValue": 10261.89, "marketValueChange": 2.62, "tradeNum": 68, "gainNum": 25, "loseNum": 9, "fromDate": "2024-03-11 13:30:00", "toDate": "2025-03-10 19:30:00", "positionSize": 139, "positionPrice": 77.94, "startingCash": 10000, "cash": 808.5, "arguments": "(BUY:SMA30 SELL:BollTop Cash 10K)", "winner_rate": 0.74, "extend": ""}, {"symbol": "MU", "timeframe": 60, "strategy": "Revival2", "realized": 161.35, "change": 43.83, "unrealized": -941.04, "unrealizedValueChange": -9.41, "realizedValueChange": 1.61, "marketValue": 9220.32, "marketValueChange": -7.8, "tradeNum": 90, "gainNum": 28, "loseNum": 17, "fromDate": "2024-03-11 13:30:00", "toDate": "2025-03-10 19:30:00", "positionSize": 96, "positionPrice": 97.16, "startingCash": 10000, "cash": 833.76, "arguments": "(BUY:SMA30 SELL:BollTop Cash 10K)", "winner_rate": 0.62, "extend": ""}, {"symbol": "LULU", "timeframe": 60, "strategy": "Revival2", "realized": -1811.66, "change": -178.09, "unrealized": -513.17, "unrealizedValueChange": -5.13, "realizedValueChange": -18.12, "marketValue": 7675.17, "marketValueChange": -23.25, "tradeNum": 81, "gainNum": 14, "loseNum": 24, "fromDate": "2024-03-11 13:30:00", "toDate": "2025-03-10 19:30:00", "positionSize": 12, "positionPrice": 378.78, "startingCash": 10000, "cash": 3642.99, "arguments": "(BUY:SMA30 SELL:BollTop Cash 10K)", "winner_rate": 0.37, "extend": ""}, {"symbol": "META", "timeframe": 60, "strategy": "Revival2", "realized": 2731.78, "change": 251.31, "unrealized": -635.07, "unrealizedValueChange": -6.35, "realizedValueChange": 27.32, "marketValue": 12096.7, "marketValueChange": 20.97, "tradeNum": 97, "gainNum": 39, "loseNum": 7, "fromDate": "2024-03-11 13:30:00", "toDate": "2025-03-10 19:30:00", "positionSize": 10, "positionPrice": 662.71, "startingCash": 10000, "cash": 6104.7, "arguments": "(BUY:SMA30 SELL:BollTop Cash 10K)", "winner_rate": 0.85, "extend": ""}, {"symbol": "BX", "timeframe": 60, "strategy": "Revival2", "realized": 4496.92, "change": 396.75, "unrealized": -1879.2, "unrealizedValueChange": -18.79, "realizedValueChange": 44.97, "marketValue": 12617.72, "marketValueChange": 26.18, "tradeNum": 100, "gainNum": 47, "loseNum": 5, "fromDate": "2024-03-11 13:30:00", "toDate": "2025-03-10 19:30:00", "positionSize": 70, "positionPrice": 166.12, "startingCash": 10000, "cash": 2868.82, "arguments": "(BUY:SMA30 SELL:BollTop Cash 10K)", "winner_rate": 0.9, "extend": ""}, {"symbol": "GS", "timeframe": 60, "strategy": "Revival2", "realized": 2076.15, "change": 210.87, "unrealized": -551.76, "unrealizedValueChange": -5.52, "realizedValueChange": 20.76, "marketValue": 11524.39, "marketValueChange": 15.24, "tradeNum": 71, "gainNum": 32, "loseNum": 3, "fromDate": "2024-03-11 13:30:00", "toDate": "2025-03-10 19:30:00", "positionSize": 8, "positionPrice": 599.81, "startingCash": 10000, "cash": 7277.67, "arguments": "(BUY:SMA30 SELL:BollTop Cash 10K)", "winner_rate": 0.91, "extend": ""}, {"symbol": "ADBE", "timeframe": 60, "strategy": "Revival2", "realized": 42.48, "change": 5.0, "unrealized": -609.97, "unrealizedValueChange": -6.1, "realizedValueChange": 0.42, "marketValue": 9432.52, "marketValueChange": -5.67, "tradeNum": 88, "gainNum": 18, "loseNum": 21, "fromDate": "2024-03-11 13:30:00", "toDate": "2025-03-10 19:30:00", "positionSize": 20, "positionPrice": 467.43, "startingCash": 10000, "cash": 693.92, "arguments": "(BUY:SMA30 SELL:BollTop Cash 10K)", "winner_rate": 0.46, "extend": ""}, {"symbol": "MNST", "timeframe": 60, "strategy": "Revival2", "realized": -477.37, "change": -43.14, "unrealized": 0.0, "unrealizedValueChange": 0.0, "realizedValueChange": -4.77, "marketValue": 9522.63, "marketValueChange": -4.77, "tradeNum": 94, "gainNum": 23, "loseNum": 29, "fromDate": "2024-03-11 13:30:00", "toDate": "2025-03-10 19:30:00", "positionSize": 0, "positionPrice": 0.0, "startingCash": 10000, "cash": 9522.63, "arguments": "(BUY:SMA30 SELL:BollTop Cash 10K)", "winner_rate": 0.44, "extend": ""}, {"symbol": "NUGT", "timeframe": 60, "strategy": "Revival2", "realized": 2180.19, "change": 244.98, "unrealized": 368.1, "unrealizedValueChange": 3.68, "realizedValueChange": 21.8, "marketValue": 12548.29, "marketValueChange": 25.48, "tradeNum": 97, "gainNum": 36, "loseNum": 15, "fromDate": "2024-03-11 13:30:00", "toDate": "2025-03-10 19:30:00", "positionSize": 200, "positionPrice": 47.22, "startingCash": 10000, "cash": 2736.31, "arguments": "(BUY:SMA30 SELL:BollTop Cash 10K)", "winner_rate": 0.71, "extend": ""}, {"symbol": "SSO", "timeframe": 60, "strategy": "Revival2", "realized": 2367.63, "change": 214.97, "unrealized": -1424.25, "unrealizedValueChange": -14.24, "realizedValueChange": 23.68, "marketValue": 10943.37, "marketValueChange": 9.43, "tradeNum": 88, "gainNum": 41, "loseNum": 3, "fromDate": "2024-03-11 13:30:00", "toDate": "2025-03-10 19:30:00", "positionSize": 130, "positionPrice": 94.49, "startingCash": 10000, "cash": 84.47, "arguments": "(BUY:SMA30 SELL:BollTop Cash 10K)", "winner_rate": 0.93, "extend": ""}, {"symbol": "UPRO", "timeframe": 60, "strategy": "Revival2", "realized": 3321.65, "change": 297.59, "unrealized": -2375.53, "unrealizedValueChange": -23.76, "realizedValueChange": 33.22, "marketValue": 10946.13, "marketValueChange": 9.46, "tradeNum": 88, "gainNum": 40, "loseNum": 4, "fromDate": "2024-03-11 13:30:00", "toDate": "2025-03-10 19:30:00", "positionSize": 145, "positionPrice": 91.53, "startingCash": 10000, "cash": 49.38, "arguments": "(BUY:SMA30 SELL:BollTop Cash 10K)", "winner_rate": 0.91, "extend": ""}, {"symbol": "TQQQ", "timeframe": 60, "strategy": "Revival2", "realized": 3431.99, "change": 320.67, "unrealized": -2116.28, "unrealizedValueChange": -21.16, "realizedValueChange": 34.32, "marketValue": 11315.72, "marketValueChange": 13.16, "tradeNum": 93, "gainNum": 40, "loseNum": 8, "fromDate": "2024-03-11 13:30:00", "toDate": "2025-03-10 19:30:00", "positionSize": 122, "positionPrice": 77.44, "startingCash": 10000, "cash": 3984.13, "arguments": "(BUY:SMA30 SELL:BollTop Cash 10K)", "winner_rate": 0.83, "extend": ""}, {"symbol": "ASML", "timeframe": 60, "strategy": "Revival2", "realized": -703.77, "change": -87.83, "unrealized": -661.79, "unrealizedValueChange": -6.62, "realizedValueChange": -7.04, "marketValue": 8634.44, "marketValueChange": -13.66, "tradeNum": 106, "gainNum": 14, "loseNum": 33, "fromDate": "2024-03-11 13:30:00", "toDate": "2025-03-10 19:30:00", "positionSize": 12, "positionPrice": 740.83, "startingCash": 10000, "cash": 406.26, "arguments": "(BUY:SMA30 SELL:BollTop Cash 10K)", "winner_rate": 0.3, "extend": ""}, {"symbol": "LRCX", "timeframe": 60, "strategy": "Revival2", "realized": 1052.22, "change": 125.33, "unrealized": -444.79, "unrealizedValueChange": -4.45, "realizedValueChange": 10.52, "marketValue": 10607.43, "marketValueChange": 6.07, "tradeNum": 104, "gainNum": 35, "loseNum": 19, "fromDate": "2024-03-11 13:30:00", "toDate": "2025-03-10 19:30:00", "positionSize": 103, "positionPrice": 78.24, "startingCash": 10000, "cash": 2993.67, "arguments": "(BUY:SMA30 SELL:BollTop Cash 10K)", "winner_rate": 0.65, "extend": ""}, {"symbol": "SOXL", "timeframe": 60, "strategy": "Revival2", "realized": -852.66, "change": -24.23, "unrealized": -236.94, "unrealizedValueChange": -2.37, "realizedValueChange": -8.53, "marketValue": 8910.4, "marketValueChange": -10.9, "tradeNum": 90, "gainNum": 25, "loseNum": 24, "fromDate": "2024-03-11 13:30:00", "toDate": "2025-03-10 19:30:00", "positionSize": 108, "positionPrice": 20.19, "startingCash": 10000, "cash": 6966.94, "arguments": "(BUY:SMA30 SELL:BollTop Cash 10K)", "winner_rate": 0.51, "extend": ""}, {"symbol": "UBER", "timeframe": 60, "strategy": "Revival2", "realized": 21.96, "change": 7.22, "unrealized": 170.32, "unrealizedValueChange": 1.7, "realizedValueChange": 0.22, "marketValue": 10192.28, "marketValueChange": 1.92, "tradeNum": 95, "gainNum": 23, "loseNum": 25, "fromDate": "2024-03-11 13:30:00", "toDate": "2025-03-10 19:30:00", "positionSize": 127, "positionPrice": 71.71, "startingCash": 10000, "cash": 914.93, "arguments": "(BUY:SMA30 SELL:BollTop Cash 10K)", "winner_rate": 0.48, "extend": ""}, {"symbol": "KO", "timeframe": 60, "strategy": "Revival2", "realized": 219.07, "change": 36.06, "unrealized": 0.0, "unrealizedValueChange": 0.0, "realizedValueChange": 2.19, "marketValue": 10219.07, "marketValueChange": 2.19, "tradeNum": 75, "gainNum": 33, "loseNum": 10, "fromDate": "2024-03-11 13:30:00", "toDate": "2025-03-10 19:30:00", "positionSize": 0, "positionPrice": 0.0, "startingCash": 10000, "cash": 10219.07, "arguments": "(BUY:SMA30 SELL:BollTop Cash 10K)", "winner_rate": 0.77, "extend": ""}, {"symbol": "PEP", "timeframe": 60, "strategy": "Revival2", "realized": -371.84, "change": -30.89, "unrealized": 41.9, "unrealizedValueChange": 0.42, "realizedValueChange": -3.72, "marketValue": 9670.06, "marketValueChange": -3.3, "tradeNum": 74, "gainNum": 18, "loseNum": 21, "fromDate": "2024-03-11 13:30:00", "toDate": "2025-03-10 19:30:00", "positionSize": 29, "positionPrice": 155.23, "startingCash": 10000, "cash": 5126.63, "arguments": "(BUY:SMA30 SELL:BollTop Cash 10K)", "winner_rate": 0.46, "extend": ""}, {"symbol": "NKE", "timeframe": 60, "strategy": "Revival2", "realized": 601.87, "change": 75.51, "unrealized": -13.56, "unrealizedValueChange": -0.14, "realizedValueChange": 6.02, "marketValue": 10588.3, "marketValueChange": 5.88, "tradeNum": 83, "gainNum": 28, "loseNum": 17, "fromDate": "2024-03-11 13:30:00", "toDate": "2025-03-10 19:30:00", "positionSize": 17, "positionPrice": 77.44, "startingCash": 10000, "cash": 9285.42, "arguments": "(BUY:SMA30 SELL:BollTop Cash 10K)", "winner_rate": 0.62, "extend": ""}, {"symbol": "COST", "timeframe": 60, "strategy": "Revival2", "realized": 1249.95, "change": 143.3, "unrealized": -291.88, "unrealizedValueChange": -2.92, "realizedValueChange": 12.5, "marketValue": 10958.07, "marketValueChange": 9.58, "tradeNum": 83, "gainNum": 36, "loseNum": 4, "fromDate": "2024-03-11 13:30:00", "toDate": "2025-03-10 19:30:00", "positionSize": 3, "positionPrice": 1032.52, "startingCash": 10000, "cash": 8152.38, "arguments": "(BUY:SMA30 SELL:BollTop Cash 10K)", "winner_rate": 0.9, "extend": ""}, {"symbol": "GOOGL", "timeframe": 60, "strategy": "Revival2", "realized": 866.47, "change": 96.1, "unrealized": -515.29, "unrealizedValueChange": -5.15, "realizedValueChange": 8.66, "marketValue": 10351.18, "marketValueChange": 3.51, "tradeNum": 71, "gainNum": 28, "loseNum": 10, "fromDate": "2024-03-11 13:30:00", "toDate": "2025-03-10 19:30:00", "positionSize": 36, "positionPrice": 180.58, "startingCash": 10000, "cash": 4365.64, "arguments": "(BUY:SMA30 SELL:BollTop Cash 10K)", "winner_rate": 0.74, "extend": ""}, {"symbol": "QQQ", "timeframe": 60, "strategy": "Revival2", "realized": 897.54, "change": 96.05, "unrealized": -39.1, "unrealizedValueChange": -0.39, "realizedValueChange": 8.98, "marketValue": 10858.44, "marketValueChange": 8.58, "tradeNum": 77, "gainNum": 33, "loseNum": 5, "fromDate": "2024-03-11 13:30:00", "toDate": "2025-03-10 19:30:00", "positionSize": 2, "positionPrice": 493.69, "startingCash": 10000, "cash": 9910.16, "arguments": "(BUY:SMA30 SELL:BollTop Cash 10K)", "winner_rate": 0.87, "extend": ""}, {"symbol": "DIA", "timeframe": 60, "strategy": "Revival2", "realized": 782.83, "change": 98.87, "unrealized": -231.44, "unrealizedValueChange": -2.31, "realizedValueChange": 7.83, "marketValue": 10551.39, "marketValueChange": 5.51, "tradeNum": 58, "gainNum": 29, "loseNum": 2, "fromDate": "2024-03-11 13:30:00", "toDate": "2025-03-10 19:30:00", "positionSize": 17, "positionPrice": 433.74, "startingCash": 10000, "cash": 3409.32, "arguments": "(BUY:SMA30 SELL:BollTop Cash 10K)", "winner_rate": 0.94, "extend": ""}, {"symbol": "IWM", "timeframe": 60, "strategy": "Revival2", "realized": 1070.32, "change": 101.75, "unrealized": -800.94, "unrealizedValueChange": -8.01, "realizedValueChange": 10.7, "marketValue": 10269.37, "marketValueChange": 2.69, "tradeNum": 76, "gainNum": 28, "loseNum": 10, "fromDate": "2024-03-11 13:30:00", "toDate": "2025-03-10 19:30:00", "positionSize": 39, "positionPrice": 221.94, "startingCash": 10000, "cash": 2414.77, "arguments": "(BUY:SMA30 SELL:BollTop Cash 10K)", "winner_rate": 0.74, "extend": ""}, {"symbol": "AAPL", "timeframe": 60, "strategy": "Revival2", "realized": 659.05, "change": 89.11, "unrealized": -182.85, "unrealizedValueChange": -1.83, "realizedValueChange": 6.59, "marketValue": 10476.2, "marketValueChange": 4.76, "tradeNum": 66, "gainNum": 31, "loseNum": 5, "fromDate": "2024-03-11 13:30:00", "toDate": "2025-03-10 19:30:00", "positionSize": 15, "positionPrice": 239.89, "startingCash": 10000, "cash": 7060.63, "arguments": "(BUY:SMA30 SELL:BollTop Cash 10K)", "winner_rate": 0.86, "extend": ""}, {"symbol": "AMZN", "timeframe": 60, "strategy": "Revival2", "realized": 773.87, "change": 97.59, "unrealized": -1471.04, "unrealizedValueChange": -14.71, "realizedValueChange": 7.74, "marketValue": 9302.83, "marketValueChange": -6.97, "tradeNum": 84, "gainNum": 32, "loseNum": 10, "fromDate": "2024-03-11 13:30:00", "toDate": "2025-03-10 19:30:00", "positionSize": 43, "positionPrice": 228.14, "startingCash": 10000, "cash": 963.84, "arguments": "(BUY:SMA30 SELL:BollTop Cash 10K)", "winner_rate": 0.76, "extend": ""}, {"symbol": "MSFT", "timeframe": 60, "strategy": "Revival2", "realized": 1084.66, "change": 137.55, "unrealized": -884.78, "unrealizedValueChange": -8.85, "realizedValueChange": 10.85, "marketValue": 10199.87, "marketValueChange": 2.0, "tradeNum": 91, "gainNum": 35, "loseNum": 13, "fromDate": "2024-03-11 13:30:00", "toDate": "2025-03-10 19:30:00", "positionSize": 26, "positionPrice": 413.63, "startingCash": 10000, "cash": 330.27, "arguments": "(BUY:SMA30 SELL:BollTop Cash 10K)", "winner_rate": 0.73, "extend": ""}, {"symbol": "NVDA", "timeframe": 60, "strategy": "Revival2", "realized": 5140.27, "change": 480.16, "unrealized": -2589.79, "unrealizedValueChange": -25.9, "realizedValueChange": 51.4, "marketValue": 12550.47, "marketValueChange": 25.5, "tradeNum": 86, "gainNum": 41, "loseNum": 3, "fromDate": "2024-03-11 13:30:00", "toDate": "2025-03-10 19:30:00", "positionSize": 91, "positionPrice": 135.74, "startingCash": 10000, "cash": 2787.54, "arguments": "(BUY:SMA30 SELL:BollTop Cash 10K)", "winner_rate": 0.93, "extend": ""}, {"symbol": "NFLX", "timeframe": 60, "strategy": "Revival2", "realized": 2934.21, "change": 256.92, "unrealized": -718.55, "unrealizedValueChange": -7.19, "realizedValueChange": 29.34, "marketValue": 12215.67, "marketValueChange": 22.16, "tradeNum": 85, "gainNum": 36, "loseNum": 4, "fromDate": "2024-03-11 13:30:00", "toDate": "2025-03-10 19:30:00", "positionSize": 6, "positionPrice": 989.16, "startingCash": 10000, "cash": 6999.24, "arguments": "(BUY:SMA30 SELL:BollTop Cash 10K)", "winner_rate": 0.9, "extend": ""}, {"symbol": "TSLA", "timeframe": 60, "strategy": "Revival2", "realized": 8837.89, "change": 727.35, "unrealized": -3811.33, "unrealizedValueChange": -38.11, "realizedValueChange": 88.38, "marketValue": 15026.56, "marketValueChange": 50.27, "tradeNum": 92, "gainNum": 40, "loseNum": 8, "fromDate": "2024-03-11 13:30:00", "toDate": "2025-03-10 19:30:00", "positionSize": 29, "positionPrice": 354.24, "startingCash": 10000, "cash": 8564.93, "arguments": "(BUY:SMA30 SELL:BollTop Cash 10K)", "winner_rate": 0.83, "extend": ""}, {"symbol": "TCEHY", "timeframe": 60, "strategy": "Revival2", "realized": 1407.82, "change": 188.71, "unrealized": 0.0, "unrealizedValueChange": 0.0, "realizedValueChange": 14.08, "marketValue": 11407.82, "marketValueChange": 14.08, "tradeNum": 54, "gainNum": 25, "loseNum": 7, "fromDate": "2024-03-11 13:30:00", "toDate": "2025-03-10 19:30:00", "positionSize": 0, "positionPrice": 0.0, "startingCash": 10000, "cash": 11407.82, "arguments": "(BUY:SMA30 SELL:BollTop Cash 10K)", "winner_rate": 0.78, "extend": ""}, {"symbol": "EDU", "timeframe": 60, "strategy": "Revival2", "realized": -2524.07, "change": -274.91, "unrealized": -965.74, "unrealizedValueChange": -9.66, "realizedValueChange": -25.24, "marketValue": 6510.18, "marketValueChange": -34.9, "tradeNum": 88, "gainNum": 12, "loseNum": 32, "fromDate": "2024-03-11 13:30:00", "toDate": "2025-03-10 19:30:00", "positionSize": 117, "positionPrice": 56.58, "startingCash": 10000, "cash": 855.57, "arguments": "(BUY:SMA30 SELL:BollTop Cash 10K)", "winner_rate": 0.27, "extend": ""}]